{
    "created_time": "2022-12-08T08:51:25Z",
    "files": [
        {
            "attachment_folder": "",
            "created_time": "2022-12-08T08:51:25Z",
            "id": "782",
            "modified_time": "2022-12-08T08:51:25Z",
            "name": "c#数字图像处理（一）Bitmap类、 Bitmapdata类和 Graphics类.md",
            "signature": "106375125509517",
            "tags": [
            ]
        },
        {
            "attachment_folder": "",
            "created_time": "2022-12-08T08:51:25Z",
            "id": "783",
            "modified_time": "2022-12-08T08:51:25Z",
            "name": "c#数字图像处理（三）灰度直方图.md",
            "signature": "101599121876365",
            "tags": [
            ]
        },
        {
            "attachment_folder": "",
            "created_time": "2022-12-08T08:51:26Z",
            "id": "784",
            "modified_time": "2022-12-08T08:51:26Z",
            "name": "c#数字图像处理（二）彩色图像灰度化，灰度图像二值化.md",
            "signature": "66891491157390",
            "tags": [
            ]
        },
        {
            "attachment_folder": "",
            "created_time": "2022-12-08T08:51:26Z",
            "id": "785",
            "modified_time": "2022-12-08T08:51:26Z",
            "name": "c#数字图像处理（四）线性点运算.md",
            "signature": "17314683659662",
            "tags": [
            ]
        }
    ],
    "folders": [
    ],
    "id": "781",
    "modified_time": "2022-12-08T08:51:25Z",
    "signature": "96015664391565",
    "version": 3
}
